rlagent/__init__.py
rlagent/core.py
rlagent/agents/__init__.py
rlagent/agents/replay.py
rlagent/agents/synchronous.py
rlagent/algorithms/__init__.py
rlagent/algorithms/a2c_mpi.py
rlagent/algorithms/ddpg.py
rlagent/memories/__init__.py
rlagent/memories/base.py
rlagent/memories/nstep.py
rlagent/memories/replaybuffer.py
rlagent/models/__init__.py
rlagent/models/actor.py
rlagent/models/actor_critic.py
rlagent/models/critic.py
rlagent/noises/__init__.py
rlagent/noises/ounoise.py
rlagent-0.1.4.dist-info/METADATA
rlagent-0.1.4.dist-info/RECORD
rlagent-0.1.4.dist-info/WHEEL
rlagent-0.1.4.dist-info/top_level.txt
